zgw_consumers/__init__.py
zgw_consumers/admin.py
zgw_consumers/admin_fields.py
zgw_consumers/apps.py
zgw_consumers/client.py
zgw_consumers/concurrent.py
zgw_consumers/constants.py
zgw_consumers/fields.py
zgw_consumers/mixins.py
zgw_consumers/nlx.py
zgw_consumers/py.typed
zgw_consumers/service.py
zgw_consumers/settings.py
zgw_consumers/utils.py
zgw_consumers/widgets.py
zgw_consumers/api_models/__init__.py
zgw_consumers/api_models/_camel_case.py
zgw_consumers/api_models/base.py
zgw_consumers/api_models/besluiten.py
zgw_consumers/api_models/catalogi.py
zgw_consumers/api_models/compat.py
zgw_consumers/api_models/constants.py
zgw_consumers/api_models/documenten.py
zgw_consumers/api_models/selectielijst.py
zgw_consumers/api_models/types.py
zgw_consumers/api_models/zaken.py
zgw_consumers/contrib/__init__.py
zgw_consumers/contrib/setup_configuration/__init__.py
zgw_consumers/contrib/setup_configuration/models.py
zgw_consumers/contrib/setup_configuration/steps.py
zgw_consumers/drf/__init__.py
zgw_consumers/drf/fields.py
zgw_consumers/drf/utils.py
zgw_consumers/legacy/__init__.py
zgw_consumers/legacy/nlx.py
zgw_consumers/legacy/service.py
zgw_consumers/locale/nl/LC_MESSAGES/django.po
zgw_consumers/migrations/0001_initial.py
zgw_consumers/migrations/0002_auto_20190514_0944.py
zgw_consumers/migrations/0003_auto_20190514_1009.py
zgw_consumers/migrations/0004_auto_20200113_1728.py
zgw_consumers/migrations/0005_auto_20200326_1040.py
zgw_consumers/migrations/0006_update_oas_auth.py
zgw_consumers/migrations/0007_service_nlx.py
zgw_consumers/migrations/0008_auto_20200331_1400.py
zgw_consumers/migrations/0009_auto_20200401_0829.py
zgw_consumers/migrations/0010_nlxconfig.py
zgw_consumers/migrations/0011_remove_service_extra.py
zgw_consumers/migrations/0012_auto_20210104_1039.py
zgw_consumers/migrations/0013_oas_field.py
zgw_consumers/migrations/0014_auto_20211217_1557.py
zgw_consumers/migrations/0015_auto_20220307_1522.py
zgw_consumers/migrations/0016_auto_20220818_1412.py
zgw_consumers-1.2.0.dist-info/licenses/LICENSE
zgw_consumers-1.2.0.dist-info/METADATA
zgw_consumers-1.2.0.dist-info/WHEEL
zgw_consumers-1.2.0.dist-info/top_level.txt
zgw_consumers-1.2.0.dist-info/RECORD
