Metadata-Version: 2.4
Name: zgw-consumers
Version: 1.2.0
Summary: Configuration for service (OpenAPI 3 or other) consumers
Author-email: Maykin Media <support@maykinmedia.nl>
License: Copyright 2022 Maykin Media
Project-URL: Homepage, https://github.com/maykinmedia/zgw-consumers
Project-URL: Documentation, https://zgw-consumers.readthedocs.io/en/latest/
Project-URL: Bug Tracker, https://github.com/maykinmedia/zgw-consumers/issues
Project-URL: Source Code, https://github.com/maykinmedia/zgw-consumers
Project-URL: Changelog, https://github.com/maykinmedia/zgw-consumers/blob/main/CHANGELOG.rst
Keywords: Django,ZGW,Common Ground,VNG,API,OpenAPI,OAS,mTLS
Classifier: Development Status :: 5 - Production/Stable
Classifier: Framework :: Django
Classifier: Framework :: Django :: 4.2
Classifier: Framework :: Django :: 5.2
Classifier: Intended Audience :: Developers
Classifier: Operating System :: Unix
Classifier: Operating System :: MacOS
Classifier: Operating System :: Microsoft :: Windows
Classifier: Programming Language :: Python :: 3.10
Classifier: Programming Language :: Python :: 3.11
Classifier: Programming Language :: Python :: 3.12
Classifier: Topic :: Software Development :: Libraries :: Python Modules
Requires-Python: >=3.10
License-File: LICENSE
Requires-Dist: django>=4.2
Requires-Dist: django-relativedelta>=2.0.0
Requires-Dist: django-solo
Requires-Dist: django-simple-certmanager>=1.4.1
Requires-Dist: requests
Requires-Dist: ape-pie
Requires-Dist: typing_extensions>=4.5.0
Requires-Dist: PyJWT>=2.0.0
Provides-Extra: db
Requires-Dist: psycopg2; extra == "db"
Provides-Extra: drf
Requires-Dist: djangorestframework; extra == "drf"
Provides-Extra: oauth2
Requires-Dist: requests-oauthlib; extra == "oauth2"
Provides-Extra: setup-configuration
Requires-Dist: django-setup-configuration>=0.6.0; extra == "setup-configuration"
Provides-Extra: testutils
Requires-Dist: Faker>=0.7.0; extra == "testutils"
Requires-Dist: factory-boy; extra == "testutils"
Requires-Dist: requests-mock; extra == "testutils"
Requires-Dist: pyyaml; extra == "testutils"
Provides-Extra: tests
Requires-Dist: django-redis; extra == "tests"
Requires-Dist: pytest; extra == "tests"
Requires-Dist: pytest-django; extra == "tests"
Requires-Dist: requests-mock; extra == "tests"
Requires-Dist: freezegun; extra == "tests"
Requires-Dist: tox; extra == "tests"
Requires-Dist: isort; extra == "tests"
Requires-Dist: black; extra == "tests"
Requires-Dist: flake8; extra == "tests"
Requires-Dist: tabulate; extra == "tests"
Requires-Dist: pyquery; extra == "tests"
Provides-Extra: coverage
Requires-Dist: pytest-cov; extra == "coverage"
Provides-Extra: docs
Requires-Dist: sphinx; extra == "docs"
Requires-Dist: sphinx-rtd-theme; extra == "docs"
Provides-Extra: release
Requires-Dist: bump-my-version; extra == "release"
Dynamic: license-file
